htmlmaster/__init__.py
htmlmaster/_typing.py
htmlmaster/_version.py
htmlmaster/abc.py
htmlmaster/core.py
htmlmaster-0.0.5.dist-info/METADATA
htmlmaster-0.0.5.dist-info/WHEEL
htmlmaster-0.0.5.dist-info/licenses/LICENSE
htmlmaster-0.0.5.dist-info/RECORD
